protobase_client/__init__.py
protobase_client/auth.py
protobase_client-2.0.0.dist-info/LICENSE
protobase_client-2.0.0.dist-info/METADATA
protobase_client-2.0.0.dist-info/WHEEL
protobase_client-2.0.0.dist-info/top_level.txt
protobase_client-2.0.0.dist-info/RECORD
