Metadata-Version: 2.1
Name: protobase-client
Version: 2.0.0
Summary: A Python client for the ProtoBase authentication API
Home-page: https://github.com/AkiTheMemeGod/ProtoBase
Author: AkiTheMemeGod
Author-email: k.akashkumar@gmail.com
Classifier: Programming Language :: Python :: 3
Classifier: License :: OSI Approved :: MIT License
Classifier: Operating System :: OS Independent
Requires-Python: >=3.6
License-File: LICENSE
Requires-Dist: requests
